pycleanup/__init__.py
pycleanup/__main__.py
pycleanup/func.py
pycleanup-0.0.1.dist-info/DESCRIPTION.rst
pycleanup-0.0.1.dist-info/METADATA
pycleanup-0.0.1.dist-info/RECORD
pycleanup-0.0.1.dist-info/WHEEL
pycleanup-0.0.1.dist-info/entry_points.txt
pycleanup-0.0.1.dist-info/metadata.json
pycleanup-0.0.1.dist-info/top_level.txt
