Metadata-Version: 2.0
Name: pycleanup
Version: 0.0.1
Summary: Clean up your working directory.
Home-page: https://github.com/axju/pyclean
Author: Axel Juraske
Author-email: axel.juraske@short-report.de
License: MIT
Keywords: Clean up
Platform: UNKNOWN
